{"success": true, "transactions": [{"type": "payment", "amount": {"value": "10.0000000", "currency": "XLM"}, "createdAt": "2025-04-25T12:30:00Z", "transaction": {"txHash": "c1d5a98e3b4f2c6d7a9b8c7d6e5f4a3b2c1d0e", "ledger": 12345}, "status": "completed", "memo": "Test payment"}, {"type": "payment", "amount": {"value": "5.0000000", "currency": "XLM"}, "createdAt": "2025-04-24T14:45:00Z", "transaction": {"txHash": "a7b8c9d0e1f2a3b4c5d6e7f8a9b0c1d2e3f4a5", "ledger": 12340}, "status": "completed", "memo": "Donation"}], "pagination": {"hasMore": false, "page": 1, "limit": 10}}